<?xml version="1.0" encoding="utf-8"?>
<Trajectories>
   <Trajectory>
      <Start>
         <x range="0.20121"/>
         <y range="0.20000"/>
         <velocity range="0.20121">11.00000</velocity>
         <orientation range="0.01000"/>
      </Start>
      <Final>
         <x range="0.00680">29.99213</x>
         <y range="0.00670">11.80571</y>
         <velocity range="0.03000">10.99998</velocity>
         <orientation range="0.00300">0.74755</orientation>
      </Final>
      <timeStepSize>3.00000</timeStepSize>
      <Path>
         <State>
            <x range="0.61223">0.40776</x>
            <y range="0.20345">0.00070</y>
            <orientation range="0.07570">0.01376</orientation>
            <velocity range="0.90322">11.03091</velocity>
         </State>
         <State>
            <x range="0.57320">1.21528</x>
            <y range="0.18852">0.00770</y>
            <orientation range="0.11055">0.03176</orientation>
            <velocity range="1.19221">11.03748</velocity>
         </State>
         <State>
            <x range="0.50505">2.03876</x>
            <y range="0.13297">0.02950</y>
            <orientation range="0.11244">0.03717</orientation>
            <velocity range="1.19587">11.03701</velocity>
         </State>
         <State>
            <x range="0.44855">2.87766</x>
            <y range="0.07952">0.07989</y>
            <orientation range="0.08518">0.06183</orientation>
            <velocity range="0.92973">11.02665</velocity>
         </State>
         <State>
            <x range="0.43067">3.71481</x>
            <y range="0.07120">0.15404</y>
            <orientation range="0.02546">0.08846</orientation>
            <velocity range="0.09716">10.97445</velocity>
         </State>
         <State>
            <x range="0.42609">4.53247</x>
            <y range="0.07378">0.22869</y>
            <orientation range="0.03008">0.10520</orientation>
            <velocity range="0.14413">10.96322</velocity>
         </State>
         <State>
            <x range="0.41929">5.34916</x>
            <y range="0.07012">0.32152</y>
            <orientation range="0.03095">0.12471</orientation>
            <velocity range="0.14563">10.96320</velocity>
         </State>
         <State>
            <x range="0.41469">6.16670</x>
            <y range="0.06721">0.43315</y>
            <orientation range="0.02334">0.13502</orientation>
            <velocity range="0.12659">10.97421</velocity>
         </State>
         <State>
            <x range="0.41391">6.98293</x>
            <y range="0.07268">0.55998</y>
            <orientation range="0.01460">0.16093</orientation>
            <velocity range="0.03278">10.99908</velocity>
         </State>
         <State>
            <x range="0.41273">7.79518</x>
            <y range="0.08116">0.69926</y>
            <orientation range="0.01402">0.17923</orientation>
            <velocity range="0.05405">10.99732</velocity>
         </State>
         <State>
            <x range="0.41035">8.60521</x>
            <y range="0.08743">0.85245</y>
            <orientation range="0.01539">0.19757</orientation>
            <velocity range="0.05679">10.99764</velocity>
         </State>
         <State>
            <x range="0.40832">9.41339</x>
            <y range="0.09396">1.02131</y>
            <orientation range="0.01682">0.21267</orientation>
            <velocity range="0.05716">10.99781</velocity>
         </State>
         <State>
            <x range="0.40762">10.21768</x>
            <y range="0.10280">1.20571</y>
            <orientation range="0.01484">0.23636</orientation>
            <velocity range="0.03212">10.99894</velocity>
         </State>
         <State>
            <x range="0.40615">11.01720</x>
            <y range="0.11107">1.40622</y>
            <orientation range="0.01401">0.25461</orientation>
            <velocity range="0.05025">10.99855</velocity>
         </State>
         <State>
            <x range="0.40353">11.81336</x>
            <y range="0.11760">1.61986</y>
            <orientation range="0.01491">0.27312</orientation>
            <velocity range="0.05376">10.99860</velocity>
         </State>
         <State>
            <x range="0.40094">12.60665</x>
            <y range="0.12410">1.84858</y>
            <orientation range="0.01739">0.28741</orientation>
            <velocity range="0.05424">10.99863</velocity>
         </State>
         <State>
            <x range="0.39959">13.39492</x>
            <y range="0.13286">2.09272</y>
            <orientation range="0.01550">0.31213</orientation>
            <velocity range="0.03210">10.99880</velocity>
         </State>
         <State>
            <x range="0.39762">14.17703</x>
            <y range="0.14049">2.35303</y>
            <orientation range="0.01485">0.33000</orientation>
            <velocity range="0.05005">10.99838</velocity>
         </State>
         <State>
            <x range="0.39453">14.95474</x>
            <y range="0.14680">2.62604</y>
            <orientation range="0.01477">0.34791</orientation>
            <velocity range="0.05369">10.99850</velocity>
         </State>
         <State>
            <x range="0.39131">15.72873</x>
            <y range="0.15339">2.91352</y>
            <orientation range="0.01753">0.36238</orientation>
            <velocity range="0.05420">10.99854</velocity>
         </State>
         <State>
            <x range="0.38936">16.49657</x>
            <y range="0.16220">3.21589</y>
            <orientation range="0.01540">0.38719</orientation>
            <velocity range="0.03211">10.99875</velocity>
         </State>
         <State>
            <x range="0.38693">17.25693</x>
            <y range="0.16925">3.53396</y>
            <orientation range="0.01478">0.40513</orientation>
            <velocity range="0.05014">10.99838</velocity>
         </State>
         <State>
            <x range="0.38335">18.01185</x>
            <y range="0.17532">3.86489</y>
            <orientation range="0.01478">0.42300</orientation>
            <velocity range="0.05376">10.99852</velocity>
         </State>
         <State>
            <x range="0.37947">18.76215</x>
            <y range="0.18193">4.20953</y>
            <orientation range="0.01753">0.43739</orientation>
            <velocity range="0.05426">10.99856</velocity>
         </State>
         <State>
            <x range="0.37696">19.50528</x>
            <y range="0.19057">4.56847</y>
            <orientation range="0.01519">0.46200</orientation>
            <velocity range="0.03211">10.99881</velocity>
         </State>
         <State>
            <x range="0.37412">20.23972</x>
            <y range="0.19707">4.94224</y>
            <orientation range="0.01466">0.47999</orientation>
            <velocity range="0.05015">10.99850</velocity>
         </State>
         <State>
            <x range="0.37005">20.96768</x>
            <y range="0.20282">5.32913</y>
            <orientation range="0.01490">0.49797</orientation>
            <velocity range="0.05375">10.99863</velocity>
         </State>
         <State>
            <x range="0.36553">21.69011</x>
            <y range="0.20941">5.72891</y>
            <orientation range="0.01744">0.51227</orientation>
            <velocity range="0.05425">10.99868</velocity>
         </State>
         <State>
            <x range="0.36249">22.40443</x>
            <y range="0.21780">6.14231</y>
            <orientation range="0.01507">0.53667</orientation>
            <velocity range="0.03210">10.99896</velocity>
         </State>
         <State>
            <x range="0.35925">23.10890</x>
            <y range="0.22371">6.56956</y>
            <orientation range="0.01458">0.55467</orientation>
            <velocity range="0.05013">10.99871</velocity>
         </State>
         <State>
            <x range="0.35473">23.80594</x>
            <y range="0.22903">7.01009</y>
            <orientation range="0.01488">0.57258</orientation>
            <velocity range="0.05373">10.99886</velocity>
         </State>
         <State>
            <x range="0.34963">24.49664</x>
            <y range="0.23557">7.46253</y>
            <orientation range="0.01741">0.58678</orientation>
            <velocity range="0.05423">10.99891</velocity>
         </State>
         <State>
            <x range="0.34608">25.17832</x>
            <y range="0.24372">7.92782</y>
            <orientation range="0.01495">0.61102</orientation>
            <velocity range="0.03209">10.99921</velocity>
         </State>
         <State>
            <x range="0.34246">25.84906</x>
            <y range="0.24905">8.40599</y>
            <orientation range="0.01449">0.62902</orientation>
            <velocity range="0.05009">10.99900</velocity>
         </State>
         <State>
            <x range="0.33754">26.51147</x>
            <y range="0.25387">8.89746</y>
            <orientation range="0.01485">0.64683</orientation>
            <velocity range="0.05370">10.99917</velocity>
         </State>
         <State>
            <x range="0.33188">27.16678</x>
            <y range="0.26030">9.39979</y>
            <orientation range="0.01736">0.66091</orientation>
            <velocity range="0.05420">10.99922</velocity>
         </State>
         <State>
            <x range="0.32786">27.81225</x>
            <y range="0.26817">9.91417</y>
            <orientation range="0.01475">0.68492</orientation>
            <velocity range="0.03208">10.99954</velocity>
         </State>
         <State>
            <x range="0.32389">28.44577</x>
            <y range="0.27308">10.44049</y>
            <orientation range="0.01437">0.70298</orientation>
            <velocity range="0.05006">10.99939</velocity>
         </State>
         <State>
            <x range="0.31858">29.07014</x>
            <y range="0.27722">10.97974</y>
            <orientation range="0.01481">0.72065</orientation>
            <velocity range="0.05367">10.99957</velocity>
         </State>
         <State>
            <x range="0.31243">29.68669</x>
            <y range="0.28348">11.52901</y>
            <orientation range="0.01727">0.73462</orientation>
            <velocity range="0.05417">10.99963</velocity>
         </State>
      </Path>
   </Trajectory>
   <Trajectory>
      <Start>
         <x range="0.20121"/>
         <y range="0.20000"/>
         <velocity range="0.20121">11.00000</velocity>
         <orientation range="0.01000"/>
      </Start>
      <Final>
         <x range="0.00537">32.80699</x>
         <y range="0.00573">3.08470</y>
         <velocity range="0.03000">11.00000</velocity>
         <orientation range="0.00300">0.18688</orientation>
      </Final>
      <timeStepSize>3.00000</timeStepSize>
      <Path>
         <State>
            <x range="0.61187">0.40744</x>
            <y range="0.20301">0.00027</y>
            <orientation range="0.07595">0.00617</orientation>
            <velocity range="0.88168">11.03070</velocity>
         </State>
         <State>
            <x range="0.57179">1.21486</x>
            <y range="0.18587">0.00341</y>
            <orientation range="0.10379">0.00787</orientation>
            <velocity range="1.15987">11.03736</velocity>
         </State>
         <State>
            <x range="0.50312">2.03938</x>
            <y range="0.12777">0.00967</y>
            <orientation range="0.10455">0.00853</orientation>
            <velocity range="1.16461">11.03675</velocity>
         </State>
         <State>
            <x range="0.44751">2.87985</x>
            <y range="0.05947">0.01898</y>
            <orientation range="0.09219">0.01396</orientation>
            <velocity range="0.91626">11.02525</velocity>
         </State>
         <State>
            <x range="0.43047">3.71889</x>
            <y range="0.03943">0.03973</y>
            <orientation range="0.01294">0.02219</orientation>
            <velocity range="0.08422">10.97342</velocity>
         </State>
         <State>
            <x range="0.42655">4.53999</x>
            <y range="0.03696">0.05563</y>
            <orientation range="0.01852">0.02788</orientation>
            <velocity range="0.12683">10.96163</velocity>
         </State>
         <State>
            <x range="0.42081">5.36186</x>
            <y range="0.02882">0.07798</y>
            <orientation range="0.02050">0.03049</orientation>
            <velocity range="0.12836">10.96163</velocity>
         </State>
         <State>
            <x range="0.41758">6.18617</x>
            <y range="0.02238">0.10772</y>
            <orientation range="0.01782">0.03370</orientation>
            <velocity range="0.11381">10.97341</velocity>
         </State>
         <State>
            <x range="0.41796">7.01103</x>
            <y range="0.02300">0.14131</y>
            <orientation range="0.00610">0.04035</orientation>
            <velocity range="0.03213">10.99985</velocity>
         </State>
         <State>
            <x range="0.41783">7.83458</x>
            <y range="0.02534">0.17601</y>
            <orientation range="0.00675">0.04584</orientation>
            <velocity range="0.05062">10.99919</velocity>
         </State>
         <State>
            <x range="0.41677">8.65852</x>
            <y range="0.02613">0.21448</y>
            <orientation range="0.00789">0.04977</orientation>
            <velocity range="0.05404">10.99932</velocity>
         </State>
         <State>
            <x range="0.41646">9.48308</x>
            <y range="0.02737">0.25745</y>
            <orientation range="0.00809">0.05223</orientation>
            <velocity range="0.05452">10.99939</velocity>
         </State>
         <State>
            <x range="0.41737">10.30682</x>
            <y range="0.03041">0.30418</y>
            <orientation range="0.00601">0.05908</orientation>
            <velocity range="0.03180">10.99987</velocity>
         </State>
         <State>
            <x range="0.41731">11.12961</x>
            <y range="0.03278">0.35450</y>
            <orientation range="0.00655">0.06461</orientation>
            <velocity range="0.04874">10.99983</velocity>
         </State>
         <State>
            <x range="0.41632">11.95271</x>
            <y range="0.03375">0.40843</y>
            <orientation range="0.00771">0.06857</orientation>
            <velocity range="0.05254">10.99984</velocity>
         </State>
         <State>
            <x range="0.41604">12.77635</x>
            <y range="0.03512">0.46680</y>
            <orientation range="0.00805">0.07100</orientation>
            <velocity range="0.05308">10.99984</velocity>
         </State>
         <State>
            <x range="0.41694">13.59907</x>
            <y range="0.03817">0.52889</y>
            <orientation range="0.00600">0.07782</orientation>
            <velocity range="0.03180">10.99985</velocity>
         </State>
         <State>
            <x range="0.41686">14.42075</x>
            <y range="0.04042">0.59469</y>
            <orientation range="0.00654">0.08335</orientation>
            <velocity range="0.04874">10.99983</velocity>
         </State>
         <State>
            <x range="0.41583">15.24268</x>
            <y range="0.04144">0.66403</y>
            <orientation range="0.00771">0.08730</orientation>
            <velocity range="0.05254">10.99983</velocity>
         </State>
         <State>
            <x range="0.41550">16.06510</x>
            <y range="0.04286">0.73780</y>
            <orientation range="0.00804">0.08973</orientation>
            <velocity range="0.05308">10.99983</velocity>
         </State>
         <State>
            <x range="0.41638">16.88652</x>
            <y range="0.04593">0.81524</y>
            <orientation range="0.00598">0.09652</orientation>
            <velocity range="0.03180">10.99985</velocity>
         </State>
         <State>
            <x range="0.41626">17.70682</x>
            <y range="0.04806">0.89640</y>
            <orientation range="0.00654">0.10205</orientation>
            <velocity range="0.04875">10.99983</velocity>
         </State>
         <State>
            <x range="0.41519">18.52730</x>
            <y range="0.04910">0.98113</y>
            <orientation range="0.00771">0.10599</orientation>
            <velocity range="0.05254">10.99983</velocity>
         </State>
         <State>
            <x range="0.41481">19.34821</x>
            <y range="0.05058">1.07026</y>
            <orientation range="0.00802">0.10843</orientation>
            <velocity range="0.05308">10.99984</velocity>
         </State>
         <State>
            <x range="0.41566">20.16805</x>
            <y range="0.05367">1.16300</y>
            <orientation range="0.00597">0.11519</orientation>
            <velocity range="0.03180">10.99986</velocity>
         </State>
         <State>
            <x range="0.41552">20.98668</x>
            <y range="0.05570">1.25943</y>
            <orientation range="0.00654">0.12071</orientation>
            <velocity range="0.04876">10.99984</velocity>
         </State>
         <State>
            <x range="0.41441">21.80542</x>
            <y range="0.05673">1.35953</y>
            <orientation range="0.00771">0.12465</orientation>
            <velocity range="0.05255">10.99985</velocity>
         </State>
         <State>
            <x range="0.41398">22.62455</x>
            <y range="0.05827">1.46394</y>
            <orientation range="0.00801">0.12707</orientation>
            <velocity range="0.05309">10.99985</velocity>
         </State>
         <State>
            <x range="0.41481">23.44253</x>
            <y range="0.06137">1.57192</y>
            <orientation range="0.00597">0.13382</orientation>
            <velocity range="0.03180">10.99987</velocity>
         </State>
         <State>
            <x range="0.41464">24.25920</x>
            <y range="0.06331">1.68353</y>
            <orientation range="0.00653">0.13934</orientation>
            <velocity range="0.04877">10.99986</velocity>
         </State>
         <State>
            <x range="0.41348">25.07592</x>
            <y range="0.06432">1.79894</y>
            <orientation range="0.00770">0.14326</orientation>
            <velocity range="0.05256">10.99988</velocity>
         </State>
         <State>
            <x range="0.41301">25.89299</x>
            <y range="0.06591">1.91856</y>
            <orientation range="0.00800">0.14568</orientation>
            <velocity range="0.05310">10.99988</velocity>
         </State>
         <State>
            <x range="0.41381">26.70883</x>
            <y range="0.06904">2.04171</y>
            <orientation range="0.00596">0.15241</orientation>
            <velocity range="0.03180">10.99990</velocity>
         </State>
         <State>
            <x range="0.41362">27.52327</x>
            <y range="0.07090">2.16843</y>
            <orientation range="0.00653">0.15792</orientation>
            <velocity range="0.04878">10.99990</velocity>
         </State>
         <State>
            <x range="0.41242">28.33770</x>
            <y range="0.07187">2.29908</y>
            <orientation range="0.00769">0.16183</orientation>
            <velocity range="0.05257">10.99991</velocity>
         </State>
         <State>
            <x range="0.41190">29.15243</x>
            <y range="0.07351">2.43384</y>
            <orientation range="0.00799">0.16424</orientation>
            <velocity range="0.05311">10.99992</velocity>
         </State>
         <State>
            <x range="0.41268">29.96586</x>
            <y range="0.07667">2.57208</y>
            <orientation range="0.00582">0.17086</orientation>
            <velocity range="0.03180">10.99994</velocity>
         </State>
         <State>
            <x range="0.41245">30.77780</x>
            <y range="0.07837">2.71368</y>
            <orientation range="0.00640">0.17641</orientation>
            <velocity range="0.04880">10.99995</velocity>
         </State>
         <State>
            <x range="0.41119">31.58968</x>
            <y range="0.07926">2.85957</y>
            <orientation range="0.00763">0.18033</orientation>
            <velocity range="0.05258">10.99997</velocity>
         </State>
         <State>
            <x range="0.41064">32.40179</x>
            <y range="0.08105">3.00945</y>
            <orientation range="0.00780">0.18290</orientation>
            <velocity range="0.05312">10.99997</velocity>
         </State>
      </Path>
   </Trajectory>
   <Trajectory>
      <Start>
         <x range="0.20121"/>
         <y range="0.20000"/>
         <velocity range="0.20121">11.00000</velocity>
         <orientation range="0.01000"/>
      </Start>
      <Final>
         <x range="0.00453">33.00001</x>
         <y range="0.00500">-0.00000</y>
         <velocity range="0.03000">11.00000</velocity>
         <orientation range="0.00300">-0.00000</orientation>
      </Final>
      <timeStepSize>3.00000</timeStepSize>
      <Path>
         <State>
            <x range="0.61143">0.40703</x>
            <y range="0.20229">0.00000</y>
            <orientation range="0.06835">0.00000</orientation>
            <velocity range="0.87389">11.02731</velocity>
         </State>
         <State>
            <x range="0.57045">1.21435</x>
            <y range="0.18080">0.00000</y>
            <orientation range="0.09835">0.00000</orientation>
            <velocity range="1.14669">11.03803</velocity>
         </State>
         <State>
            <x range="0.50133">2.03916</x>
            <y range="0.12197">0.00000</y>
            <orientation range="0.09870">0.00000</orientation>
            <velocity range="1.15009">11.03806</velocity>
         </State>
         <State>
            <x range="0.44574">2.88002</x>
            <y range="0.05577">-0.00000</y>
            <orientation range="0.08789">0.00000</orientation>
            <velocity range="0.89826">11.02766</velocity>
         </State>
         <State>
            <x range="0.42881">3.71920</x>
            <y range="0.02692">0.00000</y>
            <orientation range="0.00994">0.00000</orientation>
            <velocity range="0.07453">10.97347</velocity>
         </State>
         <State>
            <x range="0.42523">4.54070</x>
            <y range="0.02428">0.00000</y>
            <orientation range="0.01485">-0.00000</orientation>
            <velocity range="0.11390">10.96170</velocity>
         </State>
         <State>
            <x range="0.42009">5.36295</x>
            <y range="0.01624">-0.00000</y>
            <orientation range="0.01502">-0.00000</orientation>
            <velocity range="0.11543">10.96170</velocity>
         </State>
         <State>
            <x range="0.41739">6.18761</x>
            <y range="0.00802">-0.00000</y>
            <orientation range="0.01345">0.00000</orientation>
            <velocity range="0.10413">10.97349</velocity>
         </State>
         <State>
            <x range="0.41795">7.01294</x>
            <y range="0.00640">-0.00000</y>
            <orientation range="0.00319">-0.00000</orientation>
            <velocity range="0.03191">10.99995</velocity>
         </State>
         <State>
            <x range="0.41790">7.83728</x>
            <y range="0.00635">-0.00000</y>
            <orientation range="0.00485">0.00000</orientation>
            <velocity range="0.04920">10.99936</velocity>
         </State>
         <State>
            <x range="0.41696">8.66217</x>
            <y range="0.00543">0.00000</y>
            <orientation range="0.00538">-0.00000</orientation>
            <velocity range="0.05289">10.99949</velocity>
         </State>
         <State>
            <x range="0.41679">9.48780</x>
            <y range="0.00506">0.00000</y>
            <orientation range="0.00546">-0.00000</orientation>
            <velocity range="0.05344">10.99956</velocity>
         </State>
         <State>
            <x range="0.41777">10.31283</x>
            <y range="0.00618">-0.00000</y>
            <orientation range="0.00317">-0.00000</orientation>
            <velocity range="0.03170">11.00000</velocity>
         </State>
         <State>
            <x range="0.41778">11.13723</x>
            <y range="0.00614">-0.00000</y>
            <orientation range="0.00474">-0.00000</orientation>
            <velocity range="0.04815">11.00000</velocity>
         </State>
         <State>
            <x range="0.41691">11.96216</x>
            <y range="0.00530">-0.00000</y>
            <orientation range="0.00528">0.00000</orientation>
            <velocity range="0.05205">11.00000</velocity>
         </State>
         <State>
            <x range="0.41678">12.78780</x>
            <y range="0.00506">-0.00000</y>
            <orientation range="0.00537">0.00000</orientation>
            <velocity range="0.05261">11.00000</velocity>
         </State>
         <State>
            <x range="0.41777">13.61283</x>
            <y range="0.00618">0.00000</y>
            <orientation range="0.00317">0.00000</orientation>
            <velocity range="0.03170">11.00000</velocity>
         </State>
         <State>
            <x range="0.41778">14.43722</x>
            <y range="0.00614">0.00000</y>
            <orientation range="0.00474">-0.00000</orientation>
            <velocity range="0.04815">11.00000</velocity>
         </State>
         <State>
            <x range="0.41691">15.26216</x>
            <y range="0.00530">-0.00000</y>
            <orientation range="0.00528">0.00000</orientation>
            <velocity range="0.05204">11.00000</velocity>
         </State>
         <State>
            <x range="0.41678">16.08780</x>
            <y range="0.00506">-0.00000</y>
            <orientation range="0.00537">0.00000</orientation>
            <velocity range="0.05261">11.00000</velocity>
         </State>
         <State>
            <x range="0.41777">16.91283</x>
            <y range="0.00618">-0.00000</y>
            <orientation range="0.00317">-0.00000</orientation>
            <velocity range="0.03170">11.00000</velocity>
         </State>
         <State>
            <x range="0.41778">17.73722</x>
            <y range="0.00614">-0.00000</y>
            <orientation range="0.00474">0.00000</orientation>
            <velocity range="0.04815">11.00000</velocity>
         </State>
         <State>
            <x range="0.41691">18.56216</x>
            <y range="0.00530">-0.00000</y>
            <orientation range="0.00528">0.00000</orientation>
            <velocity range="0.05204">11.00000</velocity>
         </State>
         <State>
            <x range="0.41678">19.38780</x>
            <y range="0.00506">-0.00000</y>
            <orientation range="0.00537">0.00000</orientation>
            <velocity range="0.05261">11.00000</velocity>
         </State>
         <State>
            <x range="0.41777">20.21283</x>
            <y range="0.00618">0.00000</y>
            <orientation range="0.00317">0.00000</orientation>
            <velocity range="0.03170">11.00000</velocity>
         </State>
         <State>
            <x range="0.41778">21.03722</x>
            <y range="0.00614">0.00000</y>
            <orientation range="0.00474">-0.00000</orientation>
            <velocity range="0.04815">11.00000</velocity>
         </State>
         <State>
            <x range="0.41691">21.86216</x>
            <y range="0.00530">0.00000</y>
            <orientation range="0.00528">-0.00000</orientation>
            <velocity range="0.05204">11.00000</velocity>
         </State>
         <State>
            <x range="0.41678">22.68780</x>
            <y range="0.00506">0.00000</y>
            <orientation range="0.00537">-0.00000</orientation>
            <velocity range="0.05261">11.00000</velocity>
         </State>
         <State>
            <x range="0.41777">23.51283</x>
            <y range="0.00618">0.00000</y>
            <orientation range="0.00317">0.00000</orientation>
            <velocity range="0.03170">11.00000</velocity>
         </State>
         <State>
            <x range="0.41778">24.33722</x>
            <y range="0.00614">0.00000</y>
            <orientation range="0.00474">-0.00000</orientation>
            <velocity range="0.04815">11.00000</velocity>
         </State>
         <State>
            <x range="0.41691">25.16216</x>
            <y range="0.00530">0.00000</y>
            <orientation range="0.00528">0.00000</orientation>
            <velocity range="0.05204">11.00000</velocity>
         </State>
         <State>
            <x range="0.41678">25.98780</x>
            <y range="0.00506">-0.00000</y>
            <orientation range="0.00537">0.00000</orientation>
            <velocity range="0.05261">11.00000</velocity>
         </State>
         <State>
            <x range="0.41777">26.81283</x>
            <y range="0.00618">-0.00000</y>
            <orientation range="0.00317">-0.00000</orientation>
            <velocity range="0.03170">11.00000</velocity>
         </State>
         <State>
            <x range="0.41778">27.63722</x>
            <y range="0.00614">-0.00000</y>
            <orientation range="0.00474">0.00000</orientation>
            <velocity range="0.04815">11.00000</velocity>
         </State>
         <State>
            <x range="0.41691">28.46216</x>
            <y range="0.00530">-0.00000</y>
            <orientation range="0.00528">0.00000</orientation>
            <velocity range="0.05204">11.00000</velocity>
         </State>
         <State>
            <x range="0.41678">29.28780</x>
            <y range="0.00506">-0.00000</y>
            <orientation range="0.00537">0.00000</orientation>
            <velocity range="0.05261">11.00000</velocity>
         </State>
         <State>
            <x range="0.41777">30.11283</x>
            <y range="0.00618">-0.00000</y>
            <orientation range="0.00317">-0.00000</orientation>
            <velocity range="0.03170">11.00000</velocity>
         </State>
         <State>
            <x range="0.41778">30.93722</x>
            <y range="0.00614">-0.00000</y>
            <orientation range="0.00474">0.00000</orientation>
            <velocity range="0.04815">11.00000</velocity>
         </State>
         <State>
            <x range="0.41691">31.76216</x>
            <y range="0.00530">-0.00000</y>
            <orientation range="0.00528">-0.00000</orientation>
            <velocity range="0.05204">11.00000</velocity>
         </State>
         <State>
            <x range="0.41678">32.58780</x>
            <y range="0.00506">-0.00000</y>
            <orientation range="0.00537">-0.00000</orientation>
            <velocity range="0.05261">11.00000</velocity>
         </State>
      </Path>
   </Trajectory>
   <Trajectory>
      <Start>
         <x range="0.20121"/>
         <y range="0.20000"/>
         <velocity range="0.20121">11.00000</velocity>
         <orientation range="0.01000"/>
      </Start>
      <Final>
         <x range="0.00604">32.23200</x>
         <y range="0.00627">6.11534</y>
         <velocity range="0.03000">10.99999</velocity>
         <orientation range="0.00300">0.37377</orientation>
      </Final>
      <timeStepSize>3.00000</timeStepSize>
      <Path>
         <State>
            <x range="0.61204">0.40760</x>
            <y range="0.20317">0.00042</y>
            <orientation range="0.07597">0.00964</orientation>
            <velocity range="0.88306">11.03360</velocity>
         </State>
         <State>
            <x range="0.57233">1.21519</x>
            <y range="0.18694">0.00535</y>
            <orientation range="0.10661">0.01573</orientation>
            <velocity range="1.17294">11.03655</velocity>
         </State>
         <State>
            <x range="0.50382">2.03937</x>
            <y range="0.12930">0.01703</y>
            <orientation range="0.10751">0.01756</orientation>
            <velocity range="1.17760">11.03544</velocity>
         </State>
         <State>
            <x range="0.44793">2.87936</x>
            <y range="0.06231">0.03676</y>
            <orientation range="0.09015">0.02974</orientation>
            <velocity range="0.92594">11.02353</velocity>
         </State>
         <State>
            <x range="0.43066">3.71808</x>
            <y range="0.04693">0.07916</y>
            <orientation range="0.01708">0.04390</orientation>
            <velocity range="0.08862">10.97339</velocity>
         </State>
         <State>
            <x range="0.42664">4.53843</x>
            <y range="0.04754">0.11452</y>
            <orientation range="0.02052">0.05396</orientation>
            <velocity range="0.13267">10.96163</velocity>
         </State>
         <State>
            <x range="0.42063">5.35923</x>
            <y range="0.04199">0.16006</y>
            <orientation range="0.02309">0.06214</orientation>
            <velocity range="0.13419">10.96162</velocity>
         </State>
         <State>
            <x range="0.41707">6.18219</x>
            <y range="0.03726">0.21684</y>
            <orientation range="0.01931">0.06734</orientation>
            <velocity range="0.11816">10.97331</velocity>
         </State>
         <State>
            <x range="0.41721">7.00533</x>
            <y range="0.03967">0.28159</y>
            <orientation range="0.00919">0.08087</orientation>
            <velocity range="0.03228">10.99961</velocity>
         </State>
         <State>
            <x range="0.41688">7.82659</x>
            <y range="0.04404">0.35141</y>
            <orientation range="0.00942">0.09043</orientation>
            <velocity range="0.05144">10.99880</velocity>
         </State>
         <State>
            <x range="0.41556">8.64772</x>
            <y range="0.04658">0.42846</y>
            <orientation range="0.01028">0.09896</orientation>
            <velocity range="0.05473">10.99896</velocity>
         </State>
         <State>
            <x range="0.41492">9.46901</x>
            <y range="0.04969">0.51370</y>
            <orientation range="0.01094">0.10581</orientation>
            <velocity range="0.05518">10.99904</velocity>
         </State>
         <State>
            <x range="0.41552">10.28882</x>
            <y range="0.05474">0.60662</y>
            <orientation range="0.00905">0.11836</orientation>
            <velocity range="0.03190">10.99957</velocity>
         </State>
         <State>
            <x range="0.41518">11.10690</x>
            <y range="0.05898">0.70749</y>
            <orientation range="0.00919">0.12800</orientation>
            <velocity range="0.04926">10.99945</velocity>
         </State>
         <State>
            <x range="0.41384">11.92458</x>
            <y range="0.06176">0.81534</y>
            <orientation range="0.01006">0.13651</orientation>
            <velocity range="0.05297">10.99946</velocity>
         </State>
         <State>
            <x range="0.41312">12.74213</x>
            <y range="0.06509">0.93130</y>
            <orientation range="0.01082">0.14343</orientation>
            <velocity range="0.05349">10.99947</velocity>
         </State>
         <State>
            <x range="0.41361">13.55788</x>
            <y range="0.07021">1.05482</y>
            <orientation range="0.00902">0.15587</orientation>
            <velocity range="0.03190">10.99951</velocity>
         </State>
         <State>
            <x range="0.41314">14.37158</x>
            <y range="0.07416">1.18636</y>
            <orientation range="0.00917">0.16552</orientation>
            <velocity range="0.04926">10.99941</velocity>
         </State>
         <State>
            <x range="0.41166">15.18459</x>
            <y range="0.07701">1.32483</y>
            <orientation range="0.01005">0.17403</orientation>
            <velocity range="0.05297">10.99944</velocity>
         </State>
         <State>
            <x range="0.41076">15.99726</x>
            <y range="0.08044">1.47133</y>
            <orientation range="0.01082">0.18091</orientation>
            <velocity range="0.05349">10.99945</velocity>
         </State>
         <State>
            <x range="0.41112">16.80783</x>
            <y range="0.08558">1.62528</y>
            <orientation range="0.00899">0.19332</orientation>
            <velocity range="0.03190">10.99949</velocity>
         </State>
         <State>
            <x range="0.41054">17.61600</x>
            <y range="0.08932">1.78712</y>
            <orientation range="0.00915">0.20298</orientation>
            <velocity range="0.04928">10.99941</velocity>
         </State>
         <State>
            <x range="0.40890">18.42323</x>
            <y range="0.09212">1.95608</y>
            <orientation range="0.01004">0.21147</orientation>
            <velocity range="0.05299">10.99945</velocity>
         </State>
         <State>
            <x range="0.40784">19.22988</x>
            <y range="0.09564">2.13286</y>
            <orientation range="0.01082">0.21832</orientation>
            <velocity range="0.05351">10.99946</velocity>
         </State>
         <State>
            <x range="0.40807">20.03416</x>
            <y range="0.10081">2.31697</y>
            <orientation range="0.00896">0.23070</orientation>
            <velocity range="0.03190">10.99951</velocity>
         </State>
         <State>
            <x range="0.40737">20.83569</x>
            <y range="0.10436">2.50878</y>
            <orientation range="0.00913">0.24036</orientation>
            <velocity range="0.04929">10.99945</velocity>
         </State>
         <State>
            <x range="0.40559">21.63602</x>
            <y range="0.10707">2.70796</y>
            <orientation range="0.01003">0.24883</orientation>
            <velocity range="0.05300">10.99950</velocity>
         </State>
         <State>
            <x range="0.40435">22.43555</x>
            <y range="0.11067">2.91470</y>
            <orientation range="0.01081">0.25565</orientation>
            <velocity range="0.05352">10.99951</velocity>
         </State>
         <State>
            <x range="0.40445">23.23242</x>
            <y range="0.11586">3.12865</y>
            <orientation range="0.00893">0.26798</orientation>
            <velocity range="0.03190">10.99957</velocity>
         </State>
         <State>
            <x range="0.40364">24.02622</x>
            <y range="0.11923">3.35009</y>
            <orientation range="0.00910">0.27764</orientation>
            <velocity range="0.04931">10.99953</velocity>
         </State>
         <State>
            <x range="0.40172">24.81855</x>
            <y range="0.12183">3.57914</y>
            <orientation range="0.01002">0.28609</orientation>
            <velocity range="0.05301">10.99958</velocity>
         </State>
         <State>
            <x range="0.40032">25.60988</x>
            <y range="0.12551">3.81548</y>
            <orientation range="0.01080">0.29287</orientation>
            <velocity range="0.05353">10.99960</velocity>
         </State>
         <State>
            <x range="0.40029">26.39826</x>
            <y range="0.13071">4.05888</y>
            <orientation range="0.00889">0.30515</orientation>
            <velocity range="0.03190">10.99967</velocity>
         </State>
         <State>
            <x range="0.39937">27.18326</x>
            <y range="0.13389">4.30954</y>
            <orientation range="0.00907">0.31480</orientation>
            <velocity range="0.04932">10.99965</velocity>
         </State>
         <State>
            <x range="0.39731">27.96653</x>
            <y range="0.13638">4.56806</y>
            <orientation range="0.01000">0.32323</orientation>
            <velocity range="0.05302">10.99971</velocity>
         </State>
         <State>
            <x range="0.39575">28.74858</x>
            <y range="0.14012">4.83357</y>
            <orientation range="0.01078">0.32997</orientation>
            <velocity range="0.05354">10.99973</velocity>
         </State>
         <State>
            <x range="0.39559">29.52743</x>
            <y range="0.14533">5.10600</y>
            <orientation range="0.00885">0.34220</orientation>
            <velocity range="0.03190">10.99981</velocity>
         </State>
         <State>
            <x range="0.39456">30.30257</x>
            <y range="0.14835">5.38546</y>
            <orientation range="0.00905">0.35184</orientation>
            <velocity range="0.04933">10.99981</velocity>
         </State>
         <State>
            <x range="0.39238">31.07574</x>
            <y range="0.15070">5.67296</y>
            <orientation range="0.00998">0.36024</orientation>
            <velocity range="0.05303">10.99988</velocity>
         </State>
         <State>
            <x range="0.39065">31.84749</x>
            <y range="0.15449">5.96719</y>
            <orientation range="0.01076">0.36693</orientation>
            <velocity range="0.05355">10.99990</velocity>
         </State>
      </Path>
   </Trajectory>
   <Trajectory>
      <Start>
         <x range="0.20121"/>
         <y range="0.20000"/>
         <velocity range="0.20121">11.00000</velocity>
         <orientation range="0.01000"/>
      </Start>
      <Final>
         <x range="0.00652">31.28711</x>
         <y range="0.00660">9.03911</y>
         <velocity range="0.03000">10.99999</velocity>
         <orientation range="0.00300">0.56066</orientation>
      </Final>
      <timeStepSize>3.00000</timeStepSize>
      <Path>
         <State>
            <x range="0.61223">0.40777</x>
            <y range="0.20330">0.00054</y>
            <orientation range="0.07493">0.01207</orientation>
            <velocity range="0.89456">11.03349</velocity>
         </State>
         <State>
            <x range="0.57297">1.21531</x>
            <y range="0.18820">0.00672</y>
            <orientation range="0.10751">0.02325</orientation>
            <velocity range="1.18451">11.03610</velocity>
         </State>
         <State>
            <x range="0.50453">2.03905</x>
            <y range="0.13209">0.02331</y>
            <orientation range="0.10868">0.02636</orientation>
            <velocity range="1.18815">11.03511</velocity>
         </State>
         <State>
            <x range="0.44817">2.87858</x>
            <y range="0.07088">0.05655</y>
            <orientation range="0.08668">0.04561</orientation>
            <velocity range="0.93122">11.02458</velocity>
         </State>
         <State>
            <x range="0.43055">3.71671</x>
            <y range="0.06047">0.11562</y>
            <orientation range="0.02132">0.06685</orientation>
            <velocity range="0.09166">10.97413</velocity>
         </State>
         <State>
            <x range="0.42631">4.53599</x>
            <y range="0.06111">0.17124</y>
            <orientation range="0.02585">0.07949</orientation>
            <velocity range="0.13680">10.96275</velocity>
         </State>
         <State>
            <x range="0.42005">5.35510</x>
            <y range="0.05622">0.24082</y>
            <orientation range="0.02701">0.09360</orientation>
            <velocity range="0.13831">10.96274</velocity>
         </State>
         <State>
            <x range="0.41611">6.17579</x>
            <y range="0.05231">0.32519</y>
            <orientation range="0.02137">0.10128</orientation>
            <velocity range="0.12114">10.97397</velocity>
         </State>
         <State>
            <x range="0.41588">6.99603</x>
            <y range="0.05619">0.42105</y>
            <orientation range="0.01163">0.12072</orientation>
            <velocity range="0.03256">10.99930</velocity>
         </State>
         <State>
            <x range="0.41518">7.81350</x>
            <y range="0.06253">0.52566</y>
            <orientation range="0.01138">0.13478</orientation>
            <velocity range="0.05281">10.99772</velocity>
         </State>
         <State>
            <x range="0.41339">8.62997</x>
            <y range="0.06702">0.64095</y>
            <orientation range="0.01290">0.14829</orientation>
            <velocity range="0.05579">10.99801</velocity>
         </State>
         <State>
            <x range="0.41218">9.44575</x>
            <y range="0.07196">0.76830</y>
            <orientation range="0.01363">0.15949</orientation>
            <velocity range="0.05621">10.99817</velocity>
         </State>
         <State>
            <x range="0.41226">10.25905</x>
            <y range="0.07893">0.90725</y>
            <orientation range="0.01230">0.17769</orientation>
            <velocity range="0.03199">10.99923</velocity>
         </State>
         <State>
            <x range="0.41144">11.06934</x>
            <y range="0.08526">1.05833</y>
            <orientation range="0.01197">0.19142</orientation>
            <velocity range="0.04965">10.99897</velocity>
         </State>
         <State>
            <x range="0.40957">11.87802</x>
            <y range="0.08978">1.21946</y>
            <orientation range="0.01254">0.20453</orientation>
            <velocity range="0.05332">10.99901</velocity>
         </State>
         <State>
            <x range="0.40808">12.68545</x>
            <y range="0.09478">1.39222</y>
            <orientation range="0.01409">0.21542</orientation>
            <velocity range="0.05383">10.99903</velocity>
         </State>
         <State>
            <x range="0.40782">13.48971</x>
            <y range="0.10186">1.57652</y>
            <orientation range="0.01225">0.23401</orientation>
            <velocity range="0.03200">10.99913</velocity>
         </State>
         <State>
            <x range="0.40673">14.29017</x>
            <y range="0.10771">1.77309</y>
            <orientation range="0.01194">0.24777</orientation>
            <velocity range="0.04973">10.99890</velocity>
         </State>
         <State>
            <x range="0.40455">15.08841</x>
            <y range="0.11231">1.97954</y>
            <orientation range="0.01253">0.26088</orientation>
            <velocity range="0.05338">10.99896</velocity>
         </State>
         <State>
            <x range="0.40267">15.88489</x>
            <y range="0.11741">2.19743</y>
            <orientation range="0.01409">0.27172</orientation>
            <velocity range="0.05389">10.99898</velocity>
         </State>
         <State>
            <x range="0.40209">16.67754</x>
            <y range="0.12447">2.42661</y>
            <orientation range="0.01215">0.29022</orientation>
            <velocity range="0.03200">10.99910</velocity>
         </State>
         <State>
            <x range="0.40074">17.46567</x>
            <y range="0.12997">2.66773</y>
            <orientation range="0.01198">0.30407</orientation>
            <velocity range="0.04975">10.99890</velocity>
         </State>
         <State>
            <x range="0.39826">18.25096</x>
            <y range="0.13447">2.91900</y>
            <orientation range="0.01245">0.31719</orientation>
            <velocity range="0.05340">10.99898</velocity>
         </State>
         <State>
            <x range="0.39601">19.03398</x>
            <y range="0.13963">3.18126</y>
            <orientation range="0.01411">0.32789</orientation>
            <velocity range="0.05391">10.99900</velocity>
         </State>
         <State>
            <x range="0.39511">19.81257</x>
            <y range="0.14665">3.45450</y>
            <orientation range="0.01209">0.34635</orientation>
            <velocity range="0.03200">10.99913</velocity>
         </State>
         <State>
            <x range="0.39349">20.58592</x>
            <y range="0.15179">3.73929</y>
            <orientation range="0.01193">0.36017</orientation>
            <velocity range="0.04977">10.99897</velocity>
         </State>
         <State>
            <x range="0.39074">21.35582</x>
            <y range="0.15613">4.03452</y>
            <orientation range="0.01237">0.37337</orientation>
            <velocity range="0.05342">10.99907</velocity>
         </State>
         <State>
            <x range="0.38813">22.12296</x>
            <y range="0.16135">4.34019</y>
            <orientation range="0.01413">0.38392</orientation>
            <velocity range="0.05392">10.99909</velocity>
         </State>
         <State>
            <x range="0.38691">22.88508</x>
            <y range="0.16832">4.65655</y>
            <orientation range="0.01202">0.40231</orientation>
            <velocity range="0.03200">10.99924</velocity>
         </State>
         <State>
            <x range="0.38505">23.64125</x>
            <y range="0.17312">4.98396</y>
            <orientation range="0.01188">0.41615</orientation>
            <velocity range="0.04977">10.99912</velocity>
         </State>
         <State>
            <x range="0.38202">24.39342</x>
            <y range="0.17723">5.32208</y>
            <orientation range="0.01235">0.42929</orientation>
            <velocity range="0.05342">10.99922</velocity>
         </State>
         <State>
            <x range="0.37905">25.14233</x>
            <y range="0.18250">5.67008</y>
            <orientation range="0.01411">0.43977</orientation>
            <velocity range="0.05392">10.99926</velocity>
         </State>
         <State>
            <x range="0.37754">25.88567</x>
            <y range="0.18938">6.02840</y>
            <orientation range="0.01187">0.45801</orientation>
            <velocity range="0.03200">10.99942</velocity>
         </State>
         <State>
            <x range="0.37546">26.62241</x>
            <y range="0.19383">6.39721</y>
            <orientation range="0.01180">0.47184</orientation>
            <velocity range="0.04978">10.99934</velocity>
         </State>
         <State>
            <x range="0.37215">27.35458</x>
            <y range="0.19774">6.77699</y>
            <orientation range="0.01244">0.48505</orientation>
            <velocity range="0.05341">10.99945</velocity>
         </State>
         <State>
            <x range="0.36883">28.08299</x>
            <y range="0.20302">7.16611</y>
            <orientation range="0.01403">0.49546</orientation>
            <velocity range="0.05392">10.99948</velocity>
         </State>
         <State>
            <x range="0.36705">28.80532</x>
            <y range="0.20978">7.56516</y>
            <orientation range="0.01180">0.51353</orientation>
            <velocity range="0.03200">10.99967</velocity>
         </State>
         <State>
            <x range="0.36475">29.52042</x>
            <y range="0.21396">7.97419</y>
            <orientation range="0.01175">0.52734</orientation>
            <velocity range="0.04977">10.99962</velocity>
         </State>
         <State>
            <x range="0.36118">30.23042</x>
            <y range="0.21750">8.39418</y>
            <orientation range="0.01241">0.54048</orientation>
            <velocity range="0.05340">10.99974</velocity>
         </State>
         <State>
            <x range="0.35754">30.93623</x>
            <y range="0.22278">8.82300</y>
            <orientation range="0.01399">0.55080</orientation>
            <velocity range="0.05391">10.99978</velocity>
         </State>
      </Path>
   </Trajectory>
   <Trajectory>
      <Start>
         <x range="0.20121"/>
         <y range="0.20000"/>
         <velocity range="0.20121">11.00000</velocity>
         <orientation range="0.01000"/>
      </Start>
      <Final>
         <x range="0.00667">26.46654</x>
         <y range="0.00638">16.68554</y>
         <velocity range="0.03000">10.99998</velocity>
         <orientation range="0.00300">1.12134</orientation>
      </Final>
      <timeStepSize>3.00000</timeStepSize>
      <Path>
         <State>
            <x range="0.61265">0.40816</x>
            <y range="0.20377">0.00101</y>
            <orientation range="0.07496">0.01651</orientation>
            <velocity range="0.91714">11.03512</velocity>
         </State>
         <State>
            <x range="0.57465">1.21594</x>
            <y range="0.19013">0.00931</y>
            <orientation range="0.11503">0.04780</orientation>
            <velocity range="1.21650">11.03955</velocity>
         </State>
         <State>
            <x range="0.50669">2.03835</x>
            <y range="0.13678">0.04081</y>
            <orientation range="0.12228">0.06111</orientation>
            <velocity range="1.22073">11.03854</velocity>
         </State>
         <State>
            <x range="0.44931">2.87510</x>
            <y range="0.09805">0.12547</y>
            <orientation range="0.08498">0.09528</orientation>
            <velocity range="0.94707">11.02596</velocity>
         </State>
         <State>
            <x range="0.43058">3.70950</x>
            <y range="0.09397">0.23063</y>
            <orientation range="0.03726">0.13287</orientation>
            <velocity range="0.10840">10.97509</velocity>
         </State>
         <State>
            <x range="0.42516">4.52250</x>
            <y range="0.10189">0.34434</y>
            <orientation range="0.04010">0.15692</orientation>
            <velocity range="0.15921">10.96425</velocity>
         </State>
         <State>
            <x range="0.41727">5.33213</x>
            <y range="0.09999">0.48304</y>
            <orientation range="0.03869">0.18838</orientation>
            <velocity range="0.16073">10.96424</velocity>
         </State>
         <State>
            <x range="0.41083">6.14071</x>
            <y range="0.09708">0.64751</y>
            <orientation range="0.03218">0.20077</orientation>
            <velocity range="0.13816">10.97495</velocity>
         </State>
         <State>
            <x range="0.40830">6.94576</x>
            <y range="0.10528">0.83581</y>
            <orientation range="0.02077">0.24144</orientation>
            <velocity range="0.03341">10.99878</velocity>
         </State>
         <State>
            <x range="0.40569">7.74321</x>
            <y range="0.11782">1.04364</y>
            <orientation range="0.01927">0.26783</orientation>
            <velocity range="0.05770">10.99685</velocity>
         </State>
         <State>
            <x range="0.40165">8.53502</x>
            <y range="0.12760">1.27155</y>
            <orientation range="0.02033">0.29635</orientation>
            <velocity range="0.05974">10.99719</velocity>
         </State>
         <State>
            <x range="0.39725">9.32166</x>
            <y range="0.13708">1.52177</y>
            <orientation range="0.02343">0.31878</orientation>
            <velocity range="0.05993">10.99737</velocity>
         </State>
         <State>
            <x range="0.39418">10.10047</x>
            <y range="0.14941">1.79517</y>
            <orientation range="0.02017">0.35387</orientation>
            <velocity range="0.03236">10.99855</velocity>
         </State>
         <State>
            <x range="0.39069">10.86954</x>
            <y range="0.16062">2.09179</y>
            <orientation range="0.01847">0.38110</orientation>
            <velocity range="0.05129">10.99778</velocity>
         </State>
         <State>
            <x range="0.38590">11.63049</x>
            <y range="0.17048">2.40771</y>
            <orientation range="0.01966">0.40904</orientation>
            <velocity range="0.05460">10.99790</velocity>
         </State>
         <State>
            <x range="0.38040">12.38397</x>
            <y range="0.18026">2.74484</y>
            <orientation range="0.02307">0.43194</orientation>
            <velocity range="0.05505">10.99796</velocity>
         </State>
         <State>
            <x range="0.37614">13.12717</x>
            <y range="0.19243">3.10396</y>
            <orientation range="0.02000">0.46665</orientation>
            <velocity range="0.03235">10.99836</velocity>
         </State>
         <State>
            <x range="0.37171">13.85794</x>
            <y range="0.20277">3.48499</y>
            <orientation range="0.01837">0.49407</orientation>
            <velocity range="0.05118">10.99768</velocity>
         </State>
         <State>
            <x range="0.36586">14.57815</x>
            <y range="0.21204">3.88516</y>
            <orientation range="0.02002">0.52231</orientation>
            <velocity range="0.05447">10.99780</velocity>
         </State>
         <State>
            <x range="0.35886">15.28881</x>
            <y range="0.22144">4.30495</y>
            <orientation range="0.02334">0.54469</orientation>
            <velocity range="0.05493">10.99786</velocity>
         </State>
         <State>
            <x range="0.35338">15.98709</x>
            <y range="0.23298">4.74543</y>
            <orientation range="0.02068">0.58008</orientation>
            <velocity range="0.03234">10.99830</velocity>
         </State>
         <State>
            <x range="0.34823">16.67012</x>
            <y range="0.24253">5.20656</y>
            <orientation range="0.01898">0.60717</orientation>
            <velocity range="0.05097">10.99759</velocity>
         </State>
         <State>
            <x range="0.34161">17.34039</x>
            <y range="0.25108">5.68553</y>
            <orientation range="0.02014">0.63544</orientation>
            <velocity range="0.05434">10.99775</velocity>
         </State>
         <State>
            <x range="0.33306">17.99936</x>
            <y range="0.25971">6.18222</y>
            <orientation range="0.02444">0.65652</orientation>
            <velocity range="0.05482">10.99784</velocity>
         </State>
         <State>
            <x range="0.32609">18.64406</x>
            <y range="0.27040">6.69817</y>
            <orientation range="0.02158">0.69353</orientation>
            <velocity range="0.03231">10.99836</velocity>
         </State>
         <State>
            <x range="0.31994">19.27063</x>
            <y range="0.27852">7.23317</y>
            <orientation range="0.02019">0.72012</orientation>
            <velocity range="0.05051">10.99755</velocity>
         </State>
         <State>
            <x range="0.31252">19.88280</x>
            <y range="0.28588">7.78507</y>
            <orientation range="0.01964">0.74701</orientation>
            <velocity range="0.05414">10.99783</velocity>
         </State>
         <State>
            <x range="0.30295">20.48218</x>
            <y range="0.29425">8.35236</y>
            <orientation range="0.02448">0.76864</orientation>
            <velocity range="0.05466">10.99794</velocity>
         </State>
         <State>
            <x range="0.29487">21.06528</x>
            <y range="0.30443">8.93683</y>
            <orientation range="0.02136">0.80561</orientation>
            <velocity range="0.03231">10.99857</velocity>
         </State>
         <State>
            <x range="0.28802">21.62800</x>
            <y range="0.31121">9.53811</y>
            <orientation range="0.01999">0.83226</orientation>
            <velocity range="0.05056">10.99780</velocity>
         </State>
         <State>
            <x range="0.27985">22.17455</x>
            <y range="0.31744">10.15575</y>
            <orientation range="0.01964">0.85907</orientation>
            <velocity range="0.05416">10.99810</velocity>
         </State>
         <State>
            <x range="0.26916">22.70682</x>
            <y range="0.32525">10.78639</y>
            <orientation range="0.02450">0.88040</orientation>
            <velocity range="0.05468">10.99822</velocity>
         </State>
         <State>
            <x range="0.26011">23.22134</x>
            <y range="0.33449">11.43200</y>
            <orientation range="0.02113">0.91713</orientation>
            <velocity range="0.03230">10.99890</velocity>
         </State>
         <State>
            <x range="0.25271">23.71353</x>
            <y range="0.34020">12.09208</y>
            <orientation range="0.01979">0.94379</orientation>
            <velocity range="0.05059">10.99821</velocity>
         </State>
         <State>
            <x range="0.24392">24.18802</x>
            <y range="0.34496">12.76703</y>
            <orientation range="0.01964">0.97049</orientation>
            <velocity range="0.05414">10.99851</velocity>
         </State>
         <State>
            <x range="0.23226">24.64699</x>
            <y range="0.35204">13.45290</y>
            <orientation range="0.02452">0.99147</orientation>
            <velocity range="0.05466">10.99864</velocity>
         </State>
         <State>
            <x range="0.22236">25.08698</x>
            <y range="0.36022">14.15130</y>
            <orientation range="0.02038">1.02754</orientation>
            <velocity range="0.03229">10.99937</velocity>
         </State>
         <State>
            <x range="0.21426">25.50329</x>
            <y range="0.36507">14.86173</y>
            <orientation range="0.01924">1.05411</orientation>
            <velocity range="0.05077">10.99887</velocity>
         </State>
         <State>
            <x range="0.20458">25.90064</x>
            <y range="0.36843">15.58454</y>
            <orientation range="0.01964">1.08098</orientation>
            <velocity range="0.05428">10.99916</velocity>
         </State>
         <State>
            <x range="0.19241">26.28108</x>
            <y range="0.37433">16.31764</y>
            <orientation range="0.02340">1.10261</orientation>
            <velocity range="0.05478">10.99927</velocity>
         </State>
      </Path>
   </Trajectory>
   <Trajectory>
      <Start>
         <x range="0.20121"/>
         <y range="0.20000"/>
         <velocity range="0.20121">11.00000</velocity>
         <orientation range="0.01000"/>
      </Start>
      <Final>
         <x range="0.00685">28.37408</x>
         <y range="0.00664">14.36850</y>
         <velocity range="0.03000">10.99998</velocity>
         <orientation range="0.00300">0.93445</orientation>
      </Final>
      <timeStepSize>3.00000</timeStepSize>
      <Path>
         <State>
            <x range="0.61245">0.40796</x>
            <y range="0.20370">0.00090</y>
            <orientation range="0.07559">0.01539</orientation>
            <velocity range="0.91032">11.03314</velocity>
         </State>
         <State>
            <x range="0.57395">1.21563</x>
            <y range="0.18972">0.00864</y>
            <orientation range="0.11465">0.04003</orientation>
            <velocity range="1.20419">11.03803</velocity>
         </State>
         <State>
            <x range="0.50595">2.03857</x>
            <y range="0.13475">0.03550</y>
            <orientation range="0.11738">0.04770</orientation>
            <velocity range="1.20815">11.03727</velocity>
         </State>
         <State>
            <x range="0.44907">2.87653</x>
            <y range="0.08868">0.10302</y>
            <orientation range="0.08381">0.07812</orientation>
            <velocity range="0.93933">11.02626</velocity>
         </State>
         <State>
            <x range="0.43083">3.71241</x>
            <y range="0.08336">0.19291</y>
            <orientation range="0.03157">0.11156</orientation>
            <velocity range="0.10325">10.97423</velocity>
         </State>
         <State>
            <x range="0.42587">4.52786</x>
            <y range="0.08909">0.28735</y>
            <orientation range="0.03481">0.13156</orientation>
            <velocity range="0.15234">10.96300</velocity>
         </State>
         <State>
            <x range="0.41857">5.34128</x>
            <y range="0.08555">0.40294</y>
            <orientation range="0.03470">0.15601</orientation>
            <velocity range="0.15385">10.96299</velocity>
         </State>
         <State>
            <x range="0.41307">6.15485</x>
            <y range="0.08210">0.54064</y>
            <orientation range="0.02854">0.16655</orientation>
            <velocity range="0.13285">10.97410</velocity>
         </State>
         <State>
            <x range="0.41143">6.96611</x>
            <y range="0.08908">0.69822</y>
            <orientation range="0.01773">0.20123</orientation>
            <velocity range="0.03308">10.99893</velocity>
         </State>
         <State>
            <x range="0.40961">7.77169</x>
            <y range="0.09967">0.87195</y>
            <orientation range="0.01665">0.22351</orientation>
            <velocity range="0.05592">10.99739</velocity>
         </State>
         <State>
            <x range="0.40647">8.57351</x>
            <y range="0.10772">1.06271</y>
            <orientation range="0.01788">0.24702</orientation>
            <velocity range="0.05830">10.99764</velocity>
         </State>
         <State>
            <x range="0.40336">9.37199</x>
            <y range="0.11571">1.27251</y>
            <orientation range="0.02020">0.26568</orientation>
            <velocity range="0.05856">10.99778</velocity>
         </State>
         <State>
            <x range="0.40158">10.16478</x>
            <y range="0.12631">1.50178</y>
            <orientation range="0.01733">0.29498</orientation>
            <velocity range="0.03224">10.99872</velocity>
         </State>
         <State>
            <x range="0.39919">10.95056</x>
            <y range="0.13595">1.75073</y>
            <orientation range="0.01608">0.31776</orientation>
            <velocity range="0.05082">10.99818</velocity>
         </State>
         <State>
            <x range="0.39554">11.73081</x>
            <y range="0.14424">2.01609</y>
            <orientation range="0.01737">0.34094</orientation>
            <velocity range="0.05421">10.99825</velocity>
         </State>
         <State>
            <x range="0.39164">12.50610</x>
            <y range="0.15257">2.29984</y>
            <orientation range="0.01993">0.35993</orientation>
            <velocity range="0.05467">10.99829</velocity>
         </State>
         <State>
            <x range="0.38903">13.27396</x>
            <y range="0.16317">2.60235</y>
            <orientation range="0.01794">0.38954</orientation>
            <velocity range="0.03223">10.99854</velocity>
         </State>
         <State>
            <x range="0.38605">14.03279</x>
            <y range="0.17245">2.92438</y>
            <orientation range="0.01656">0.41206</orientation>
            <velocity range="0.05061">10.99798</velocity>
         </State>
         <State>
            <x range="0.38178">14.78437</x>
            <y range="0.18048">3.26190</y>
            <orientation range="0.01743">0.43542</orientation>
            <velocity range="0.05407">10.99811</velocity>
         </State>
         <State>
            <x range="0.37673">15.52965</x>
            <y range="0.18831">3.61679</y>
            <orientation range="0.02096">0.45315</orientation>
            <velocity range="0.05455">10.99817</velocity>
         </State>
         <State>
            <x range="0.37306">16.26599</x>
            <y range="0.19844">3.98989</y>
            <orientation range="0.01848">0.48402</orientation>
            <velocity range="0.03221">10.99849</velocity>
         </State>
         <State>
            <x range="0.36931">16.99115</x>
            <y range="0.20682">4.38166</y>
            <orientation range="0.01754">0.50625</orientation>
            <velocity range="0.05038">10.99791</velocity>
         </State>
         <State>
            <x range="0.36433">17.70760</x>
            <y range="0.21422">4.78873</y>
            <orientation range="0.01732">0.52881</orientation>
            <velocity range="0.05398">10.99808</velocity>
         </State>
         <State>
            <x range="0.35840">18.41645</x>
            <y range="0.22205">5.21183</y>
            <orientation range="0.02090">0.54697</orientation>
            <velocity range="0.05449">10.99815</velocity>
         </State>
         <State>
            <x range="0.35385">19.11474</x>
            <y range="0.23200">5.65196</y>
            <orientation range="0.01825">0.57766</orientation>
            <velocity range="0.03221">10.99856</velocity>
         </State>
         <State>
            <x range="0.34943">19.80005</x>
            <y range="0.23945">6.10944</y>
            <orientation range="0.01741">0.60002</orientation>
            <velocity range="0.05043">10.99804</velocity>
         </State>
         <State>
            <x range="0.34376">20.47519</x>
            <y range="0.24620">6.58241</y>
            <orientation range="0.01726">0.62247</orientation>
            <velocity range="0.05401">10.99824</velocity>
         </State>
         <State>
            <x range="0.33695">21.14139</x>
            <y range="0.25392">7.06988</y>
            <orientation range="0.02077">0.64061</orientation>
            <velocity range="0.05452">10.99831</velocity>
         </State>
         <State>
            <x range="0.33162">21.79566</x>
            <y range="0.26344">7.57315</y>
            <orientation range="0.01808">0.67103</orientation>
            <velocity range="0.03220">10.99874</velocity>
         </State>
         <State>
            <x range="0.32663">22.43525</x>
            <y range="0.26998">8.09218</y>
            <orientation range="0.01727">0.69343</orientation>
            <velocity range="0.05037">10.99829</velocity>
         </State>
         <State>
            <x range="0.32035">23.06333</x>
            <y range="0.27601">8.62661</y>
            <orientation range="0.01724">0.71579</orientation>
            <velocity range="0.05395">10.99850</velocity>
         </State>
         <State>
            <x range="0.31269">23.68129</x>
            <y range="0.28346">9.17394</y>
            <orientation range="0.02075">0.73375</orientation>
            <velocity range="0.05446">10.99858</velocity>
         </State>
         <State>
            <x range="0.30662">24.28608</x>
            <y range="0.29246">9.73570</y>
            <orientation range="0.01791">0.76397</orientation>
            <velocity range="0.03218">10.99904</velocity>
         </State>
         <State>
            <x range="0.30114">24.87466</x>
            <y range="0.29821">10.31167</y>
            <orientation range="0.01713">0.78636</orientation>
            <velocity range="0.05031">10.99865</velocity>
         </State>
         <State>
            <x range="0.29431">25.45049</x>
            <y range="0.30329">10.90247</y>
            <orientation range="0.01721">0.80862</orientation>
            <velocity range="0.05390">10.99887</velocity>
         </State>
         <State>
            <x range="0.28589">26.01515</x>
            <y range="0.31042">11.50461</y>
            <orientation range="0.02072">0.82636</orientation>
            <velocity range="0.05441">10.99896</velocity>
         </State>
         <State>
            <x range="0.27915">26.56556</x>
            <y range="0.31881">12.11972</y>
            <orientation range="0.01774">0.85637</orientation>
            <velocity range="0.03217">10.99944</velocity>
         </State>
         <State>
            <x range="0.27325">27.09841</x>
            <y range="0.32392">12.74756</y>
            <orientation range="0.01698">0.87871</orientation>
            <velocity range="0.05029">10.99911</velocity>
         </State>
         <State>
            <x range="0.26596">27.61741</x>
            <y range="0.32802">13.38894</y>
            <orientation range="0.01717">0.90083</orientation>
            <velocity range="0.05388">10.99935</velocity>
         </State>
         <State>
            <x range="0.25685">28.12432</x>
            <y range="0.33457">14.04063</y>
            <orientation range="0.02068">0.91833</orientation>
            <velocity range="0.05438">10.99944</velocity>
         </State>
      </Path>
   </Trajectory>
   <Trajectory>
      <Start>
         <x range="0.20121"/>
         <y range="0.20000"/>
         <velocity range="0.20121">11.00000</velocity>
         <orientation range="0.01000"/>
      </Start>
      <Final>
         <x range="0.00625">24.30881</x>
         <y range="0.00592">18.72059</y>
         <velocity range="0.03000">10.99998</velocity>
         <orientation range="0.00300">1.30824</orientation>
      </Final>
      <timeStepSize>3.00000</timeStepSize>
      <Path>
         <State>
            <x range="0.61162">0.40704</x>
            <y range="0.20394">0.00116</y>
            <orientation range="0.07415">0.01777</orientation>
            <velocity range="1.02130">10.97464</velocity>
         </State>
         <State>
            <x range="0.57206">1.21063</x>
            <y range="0.19110">0.00999</y>
            <orientation range="0.11124">0.05303</orientation>
            <velocity range="1.27541">11.02499</velocity>
         </State>
         <State>
            <x range="0.50414">2.03339</x>
            <y range="0.14527">0.04894</y>
            <orientation range="0.12414">0.07288</orientation>
            <velocity range="1.28841">11.03870</velocity>
         </State>
         <State>
            <x range="0.44878">2.87428</x>
            <y range="0.10998">0.14412</y>
            <orientation range="0.08368">0.11048</orientation>
            <velocity range="1.00380">11.09801</velocity>
         </State>
         <State>
            <x range="0.43042">3.70652</x>
            <y range="0.10768">0.26472</y>
            <orientation range="0.04449">0.15559</orientation>
            <velocity range="0.11217">10.97793</velocity>
         </State>
         <State>
            <x range="0.42447">4.51651</x>
            <y range="0.11808">0.39788</y>
            <orientation range="0.04660">0.18473</orientation>
            <velocity range="0.16466">10.96846</velocity>
         </State>
         <State>
            <x range="0.41586">5.32146</x>
            <y range="0.11606">0.56122</y>
            <orientation range="0.04342">0.22170</orientation>
            <velocity range="0.16620">10.96847</velocity>
         </State>
         <State>
            <x range="0.40826">6.12411</x>
            <y range="0.11230">0.75362</y>
            <orientation range="0.03576">0.23519</orientation>
            <velocity range="0.14229">10.97797</velocity>
         </State>
         <State>
            <x range="0.40471">6.92190</x>
            <y range="0.12144">0.97283</y>
            <orientation range="0.02360">0.28141</orientation>
            <velocity range="0.03396">10.99855</velocity>
         </State>
         <State>
            <x range="0.40123">7.70976</x>
            <y range="0.13634">1.21438</y>
            <orientation range="0.02236">0.31273</orientation>
            <velocity range="0.05998">10.99592</velocity>
         </State>
         <State>
            <x range="0.39610">8.48968</x>
            <y range="0.14768">1.47870</y>
            <orientation range="0.02308">0.34583</orientation>
            <velocity range="0.06179">10.99620</velocity>
         </State>
         <State>
            <x range="0.39011">9.26242</x>
            <y range="0.15814">1.76868</y>
            <orientation range="0.02714">0.37151</orientation>
            <velocity range="0.06170">10.99668</velocity>
         </State>
         <State>
            <x range="0.38555">10.02496</x>
            <y range="0.17205">2.08546</y>
            <orientation range="0.02291">0.41261</orientation>
            <velocity range="0.03252">10.99842</velocity>
         </State>
         <State>
            <x range="0.38091">10.77441</x>
            <y range="0.18510">2.42878</y>
            <orientation range="0.02130">0.44490</orientation>
            <velocity range="0.05182">10.99736</velocity>
         </State>
         <State>
            <x range="0.37478">11.51261</x>
            <y range="0.19636">2.79362</y>
            <orientation range="0.02218">0.47723</orientation>
            <velocity range="0.05503">10.99753</velocity>
         </State>
         <State>
            <x range="0.36728">12.24061</x>
            <y range="0.20707">3.18248</y>
            <orientation range="0.02668">0.50360</orientation>
            <velocity range="0.05547">10.99762</velocity>
         </State>
         <State>
            <x range="0.36106">12.95512</x>
            <y range="0.22056">3.59624</y>
            <orientation range="0.02306">0.54456</orientation>
            <velocity range="0.03247">10.99821</velocity>
         </State>
         <State>
            <x range="0.35518">13.65299</x>
            <y range="0.23213">4.03470</y>
            <orientation range="0.02081">0.57630</orientation>
            <velocity range="0.05153">10.99724</velocity>
         </State>
         <State>
            <x range="0.34774">14.33653</x>
            <y range="0.24252">4.49412</y>
            <orientation range="0.02260">0.60942</orientation>
            <velocity range="0.05478">10.99740</velocity>
         </State>
         <State>
            <x range="0.33829">15.00703</x>
            <y range="0.25278">4.97508</y>
            <orientation range="0.02691">0.63527</orientation>
            <velocity range="0.05524">10.99750</velocity>
         </State>
         <State>
            <x range="0.33043">15.66133</x>
            <y range="0.26529">5.47899</y>
            <orientation range="0.02305">0.67630</orientation>
            <velocity range="0.03246">10.99815</velocity>
         </State>
         <State>
            <x range="0.32349">16.29554</x>
            <y range="0.27536">6.00486</y>
            <orientation range="0.02082">0.70809</orientation>
            <velocity range="0.05141">10.99725</velocity>
         </State>
         <State>
            <x range="0.31485">16.91255</x>
            <y range="0.28449">6.55084</y>
            <orientation range="0.02283">0.74129</orientation>
            <velocity range="0.05469">10.99743</velocity>
         </State>
         <State>
            <x range="0.30357">17.51409</x>
            <y range="0.29400">7.11550</y>
            <orientation range="0.02726">0.76656</orientation>
            <velocity range="0.05516">10.99754</velocity>
         </State>
         <State>
            <x range="0.29405">18.09695</x>
            <y range="0.30529">7.70053</y>
            <orientation range="0.02513">0.80957</orientation>
            <velocity range="0.03242">10.99821</velocity>
         </State>
         <State>
            <x range="0.28609">18.65598</x>
            <y range="0.31370">8.30567</y>
            <orientation range="0.02300">0.84038</orientation>
            <velocity range="0.05054">10.99699</velocity>
         </State>
         <State>
            <x range="0.27689">19.19591</x>
            <y range="0.32121">8.92826</y>
            <orientation range="0.02202">0.87157</orientation>
            <velocity range="0.05425">10.99738</velocity>
         </State>
         <State>
            <x range="0.26415">19.71897</x>
            <y range="0.32972">9.56623</y>
            <orientation range="0.02864">0.89631</orientation>
            <velocity range="0.05481">10.99754</velocity>
         </State>
         <State>
            <x range="0.25270">20.22094</x>
            <y range="0.33987">10.22163</y>
            <orientation range="0.02391">0.93969</orientation>
            <velocity range="0.03238">10.99846</velocity>
         </State>
         <State>
            <x range="0.24276">20.69663</x>
            <y range="0.34603">10.89326</y>
            <orientation range="0.02283">0.97008</orientation>
            <velocity range="0.05087">10.99758</velocity>
         </State>
         <State>
            <x range="0.23145">21.15165</x>
            <y range="0.35118">11.58196</y>
            <orientation range="0.02179">1.00086</orientation>
            <velocity range="0.05443">10.99795</velocity>
         </State>
         <State>
            <x range="0.21872">21.58703</x>
            <y range="0.35964">12.28365</y>
            <orientation range="0.02469">1.02976</orientation>
            <velocity range="0.05495">10.99808</velocity>
         </State>
         <State>
            <x range="0.20734">21.99857</x>
            <y range="0.36865">12.99818</y>
            <orientation range="0.02349">1.06970</orientation>
            <velocity range="0.03234">10.99883</velocity>
         </State>
         <State>
            <x range="0.19664">22.38294</x>
            <y range="0.37369">13.72615</y>
            <orientation range="0.02241">1.10018</orientation>
            <velocity range="0.05076">10.99813</velocity>
         </State>
         <State>
            <x range="0.18456">22.74503</x>
            <y range="0.37729">14.46752</y>
            <orientation range="0.02163">1.13073</orientation>
            <velocity range="0.05431">10.99848</velocity>
         </State>
         <State>
            <x range="0.17100">23.08605</x>
            <y range="0.38376">15.22003</y>
            <orientation range="0.02445">1.15949</orientation>
            <velocity range="0.05482">10.99861</velocity>
         </State>
         <State>
            <x range="0.15886">23.40184</x>
            <y range="0.39108">15.98169</y>
            <orientation range="0.02299">1.19877</orientation>
            <velocity range="0.03234">10.99932</velocity>
         </State>
         <State>
            <x range="0.14761">23.68899</x>
            <y range="0.39493">16.75344</y>
            <orientation range="0.02222">1.22976</orientation>
            <velocity range="0.05083">10.99866</velocity>
         </State>
         <State>
            <x range="0.13507">23.95261</x>
            <y range="0.39720">17.53512</y>
            <orientation range="0.02121">1.25961</orientation>
            <velocity range="0.05432">10.99907</velocity>
         </State>
         <State>
            <x range="0.12092">24.19441</x>
            <y range="0.40156">18.32497</y>
            <orientation range="0.02453">1.28792</orientation>
            <velocity range="0.05481">10.99920</velocity>
         </State>
      </Path>
   </Trajectory>
   <Trajectory>
      <Start>
         <x range="0.20121"/>
         <y range="0.20000"/>
         <velocity range="0.20121">11.00000</velocity>
         <orientation range="0.01000"/>
      </Start>
      <Final>
         <x range="0.00563">21.94491</x>
         <y range="0.00528">20.44387</y>
         <velocity range="0.03000">10.99998</velocity>
         <orientation range="0.00300">1.49513</orientation>
      </Final>
      <timeStepSize>3.00000</timeStepSize>
      <Path>
         <State>
            <x range="0.61238">0.40765</x>
            <y range="0.20353">0.00091</y>
            <orientation range="0.07390">0.01651</orientation>
            <velocity range="1.13312">10.94961</velocity>
         </State>
         <State>
            <x range="0.57533">1.20970</x>
            <y range="0.18917">0.00936</y>
            <orientation range="0.11397">0.05545</orientation>
            <velocity range="1.28732">11.00798</velocity>
         </State>
         <State>
            <x range="0.50933">2.03028</x>
            <y range="0.15090">0.05848</y>
            <orientation range="0.12335">0.08955</orientation>
            <velocity range="1.30858">11.02988</velocity>
         </State>
         <State>
            <x range="0.45081">2.87084</x>
            <y range="0.11433">0.16120</y>
            <orientation range="0.08771">0.12336</orientation>
            <velocity range="1.11178">11.14261</velocity>
         </State>
         <State>
            <x range="0.42976">3.70327</x>
            <y range="0.11050">0.29673</y>
            <orientation range="0.05341">0.17342</orientation>
            <velocity range="0.11322">10.98141</velocity>
         </State>
         <State>
            <x range="0.42292">4.51011</x>
            <y range="0.12525">0.45062</y>
            <orientation range="0.04930">0.21091</orientation>
            <velocity range="0.16634">10.97366</velocity>
         </State>
         <State>
            <x range="0.41364">5.30977</x>
            <y range="0.12768">0.63854</y>
            <orientation range="0.04246">0.25588</orientation>
            <velocity range="0.16792">10.97371</velocity>
         </State>
         <State>
            <x range="0.40515">6.10574</x>
            <y range="0.12687">0.85800</y>
            <orientation range="0.03649">0.27051</orientation>
            <velocity range="0.14349">10.98182</velocity>
         </State>
         <State>
            <x range="0.40074">6.89518</x>
            <y range="0.13914">1.10594</y>
            <orientation range="0.02785">0.32112</orientation>
            <velocity range="0.03399">10.99874</velocity>
         </State>
         <State>
            <x range="0.39615">7.67194</x>
            <y range="0.15646">1.38116</y>
            <orientation range="0.02600">0.35915</orientation>
            <velocity range="0.06134">10.99787</velocity>
         </State>
         <State>
            <x range="0.38972">8.43793</x>
            <y range="0.16879">1.68250</y>
            <orientation range="0.02660">0.39707</orientation>
            <velocity range="0.06285">10.99785</velocity>
         </State>
         <State>
            <x range="0.38187">9.19445</x>
            <y range="0.17925">2.01250</y>
            <orientation range="0.03065">0.42464</orientation>
            <velocity range="0.06260">10.99800</velocity>
         </State>
         <State>
            <x range="0.37562">9.93829</x>
            <y range="0.19402">2.37207</y>
            <orientation range="0.02591">0.47156</orientation>
            <velocity range="0.03268">10.99830</velocity>
         </State>
         <State>
            <x range="0.36962">10.66529</x>
            <y range="0.20869">2.76092</y>
            <orientation range="0.02403">0.50840</orientation>
            <velocity range="0.05230">10.99683</velocity>
         </State>
         <State>
            <x range="0.36210">11.37756</x>
            <y range="0.22129">3.17324</y>
            <orientation range="0.02439">0.54574</orientation>
            <velocity range="0.05546">10.99709</velocity>
         </State>
         <State>
            <x range="0.35236">12.07647</x>
            <y range="0.23278">3.61171</y>
            <orientation range="0.03059">0.57500</orientation>
            <velocity range="0.05591">10.99723</velocity>
         </State>
         <State>
            <x range="0.34393">12.75848</x>
            <y range="0.24737">4.07778</y>
            <orientation range="0.02598">0.62230</orientation>
            <velocity range="0.03261">10.99809</velocity>
         </State>
         <State>
            <x range="0.33645">13.41890</x>
            <y range="0.26025">4.57093</y>
            <orientation range="0.02391">0.65914</orientation>
            <velocity range="0.05181">10.99670</velocity>
         </State>
         <State>
            <x range="0.32736">14.06066</x>
            <y range="0.27146">5.08636</y>
            <orientation range="0.02468">0.69687</orientation>
            <velocity range="0.05506">10.99697</velocity>
         </State>
         <State>
            <x range="0.31514">14.68574</x>
            <y range="0.28201">5.62459</y>
            <orientation range="0.03118">0.72525</orientation>
            <velocity range="0.05553">10.99712</velocity>
         </State>
         <State>
            <x range="0.30438">15.29050</x>
            <y range="0.29487">6.18713</y>
            <orientation range="0.02485">0.77210</orientation>
            <velocity range="0.03251">10.99807</velocity>
         </State>
         <State>
            <x range="0.29446">15.86998</x>
            <y range="0.30456">6.77176</y>
            <orientation range="0.02434">0.80846</orientation>
            <velocity range="0.05179">10.99721</velocity>
         </State>
         <State>
            <x range="0.28258">16.42776</x>
            <y range="0.31329">7.37951</y>
            <orientation range="0.02471">0.84553</orientation>
            <velocity range="0.05500">10.99743</velocity>
         </State>
         <State>
            <x range="0.26950">16.96488</x>
            <y range="0.32429">8.00643</y>
            <orientation range="0.02683">0.87899</orientation>
            <velocity range="0.05543">10.99754</velocity>
         </State>
         <State>
            <x range="0.25811">17.47774</x>
            <y range="0.33596">8.65256</y>
            <orientation range="0.02570">0.92316</orientation>
            <velocity range="0.03245">10.99816</velocity>
         </State>
         <State>
            <x range="0.24714">17.96263</x>
            <y range="0.34388">9.31771</y>
            <orientation range="0.02465">0.95896</orientation>
            <velocity range="0.05113">10.99729</velocity>
         </State>
         <State>
            <x range="0.23446">18.42309</x>
            <y range="0.35049">10.00222</y>
            <orientation range="0.02429">0.99594</orientation>
            <velocity range="0.05452">10.99760</velocity>
         </State>
         <State>
            <x range="0.21955">18.86079</x>
            <y range="0.35959">10.70206</y>
            <orientation range="0.02827">1.02764</orientation>
            <velocity range="0.05499">10.99772</velocity>
         </State>
         <State>
            <x range="0.20609">19.27181</x>
            <y range="0.36930">11.41716</y>
            <orientation range="0.02681">1.07396</orientation>
            <velocity range="0.03241">10.99837</velocity>
         </State>
         <State>
            <x range="0.19348">19.65138</x>
            <y range="0.37502">12.14744</y>
            <orientation range="0.02602">1.10899</orientation>
            <velocity range="0.05063">10.99727</velocity>
         </State>
         <State>
            <x range="0.17996">20.00523</x>
            <y range="0.37915">12.89293</y>
            <orientation range="0.02325">1.14399</orientation>
            <velocity range="0.05431">10.99775</velocity>
         </State>
         <State>
            <x range="0.16453">20.33452</x>
            <y range="0.38645">13.65045</y>
            <orientation range="0.02801">1.17665</orientation>
            <velocity range="0.05485">10.99791</velocity>
         </State>
         <State>
            <x range="0.14993">20.63487</x>
            <y range="0.39441">14.41813</y>
            <orientation range="0.02646">1.22267</orientation>
            <velocity range="0.03246">10.99875</velocity>
         </State>
         <State>
            <x range="0.13667">20.90177</x>
            <y range="0.39848">15.19700</y>
            <orientation range="0.02530">1.25787</orientation>
            <velocity range="0.05101">10.99762</velocity>
         </State>
         <State>
            <x range="0.12255">21.14138</x>
            <y range="0.40088">15.98636</y>
            <orientation range="0.02300">1.29236</orientation>
            <velocity range="0.05456">10.99815</velocity>
         </State>
         <State>
            <x range="0.10625">21.35551</x>
            <y range="0.40538">16.78399</y>
            <orientation range="0.02798">1.32469</orientation>
            <velocity range="0.05508">10.99833</velocity>
         </State>
         <State>
            <x range="0.09086">21.53936</x>
            <y range="0.41063">17.58775</y>
            <orientation range="0.02574">1.37006</orientation>
            <velocity range="0.03246">10.99926</velocity>
         </State>
         <State>
            <x range="0.07714">21.68877</x>
            <y range="0.41293">18.39778</y>
            <orientation range="0.02469">1.40559</orientation>
            <velocity range="0.05118">10.99823</velocity>
         </State>
         <State>
            <x range="0.06267">21.80989</x>
            <y range="0.41362">19.21363</y>
            <orientation range="0.02274">1.43973</orientation>
            <velocity range="0.05465">10.99876</velocity>
         </State>
         <State>
            <x range="0.04604">21.90480</x>
            <y range="0.41540">20.03378</y>
            <orientation range="0.02769">1.47176</orientation>
            <velocity range="0.05515">10.99893</velocity>
         </State>
      </Path>
   </Trajectory>
</Trajectories>